dl_on_flink_pytorch/__init__.py
dl_on_flink_pytorch/flink_row_writer.py
dl_on_flink_pytorch/flink_stream_dataset.py
dl_on_flink_pytorch/pytorch_cluster_config.py
dl_on_flink_pytorch/pytorch_context.py
dl_on_flink_pytorch/pytorch_utils.py
dl_on_flink_pytorch/version.py
dl_on_flink_pytorch/flink_ml/__init__.py
dl_on_flink_pytorch/flink_ml/pytorch_estimator.py
dl_on_flink_pytorch/flink_ml/pytorch_estimator_constants.py
dl_on_flink_pytorch/flink_ml/pytorch_model_factory.py
dl_on_flink_pytorch/flink_ml/pytorch_train_entry.py
dl_on_flink_pytorch-0.5.0.dist-info/METADATA
dl_on_flink_pytorch-0.5.0.dist-info/WHEEL
dl_on_flink_pytorch-0.5.0.dist-info/top_level.txt
dl_on_flink_pytorch-0.5.0.dist-info/RECORD
