Metadata-Version: 2.1
Name: dl-on-flink-pytorch
Version: 0.5.0
Summary: UNKNOWN
Home-page: https://github.com/flink-extended/dl-on-flink
License: https://www.apache.org/licenses/LICENSE-2.0
Platform: UNKNOWN
Requires-Python: >=3.6
Requires-Dist: torch (>=1.10)
Requires-Dist: apache-flink (<1.15.0,>=1.14.0)
Requires-Dist: pandas (>=1.0)
Requires-Dist: dl-on-flink-framework (==0.5.0)
Requires-Dist: apache-flink-ml (<3.0.0,>=2.0.0)
Requires-Dist: cloudpickle (>=1.2.2)
